cs/packetstream.py
cs.packetstream-20240630.dist-info/METADATA
cs.packetstream-20240630.dist-info/WHEEL
cs.packetstream-20240630.dist-info/top_level.txt
cs.packetstream-20240630.dist-info/RECORD
