Metadata-Version: 2.1
Name: cs.packetstream
Version: 20240630
Summary: general purpose bidirectional packet stream connection
Author-email: Cameron Simpson <cs@cskk.id.au>
License: GNU General Public License v3 or later (GPLv3+)
Project-URL: Monorepo Hg/Mercurial Mirror, https://hg.sr.ht/~cameron-simpson/css
Project-URL: Monorepo Git Mirror, https://github.com/cameron-simpson/css
Project-URL: MonoRepo Commits, https://bitbucket.org/cameron_simpson/css/commits/branch/main
Project-URL: Source, https://github.com/cameron-simpson/css/blob/main/lib/python/cs/packetstream.py
Keywords: python2,python3
Classifier: Programming Language :: Python
Classifier: Programming Language :: Python :: 3
Classifier: Topic :: System :: Networking
Classifier: Development Status :: 4 - Beta
Classifier: Intended Audience :: Developers
Classifier: Operating System :: OS Independent
Classifier: License :: OSI Approved :: GNU General Public License v3 or later (GPLv3+)
Requires-Dist: cs.binary >=20240630
Requires-Dist: cs.buffer >=20240630
Requires-Dist: cs.context >=20240630
Requires-Dist: cs.deco >=20240630
Requires-Dist: cs.excutils >=20240630
Requires-Dist: cs.later >=20240630
Requires-Dist: cs.logutils >=20240630
Requires-Dist: cs.pfx >=20240630
Requires-Dist: cs.predicate >=20210306
Requires-Dist: cs.progress >=20240412
Requires-Dist: cs.queues >=20240412
Requires-Dist: cs.resources >=20240630
Requires-Dist: cs.result >=20240630
Requires-Dist: cs.seq >=20221118
Requires-Dist: cs.threads >=20240630
Requires-Dist: cs.units
